PixelKey/__init__.py
PixelKey/core.py
PixelKey-0.1.0.dist-info/LICENSE
PixelKey-0.1.0.dist-info/METADATA
PixelKey-0.1.0.dist-info/WHEEL
PixelKey-0.1.0.dist-info/top_level.txt
PixelKey-0.1.0.dist-info/RECORD
