Metadata-Version: 2.1
Name: PixelKey
Version: 0.1.0
Summary: AES-GCM encryption with key derivation from image pixels and nonce hiding in image region.
Home-page: https://github.com/Abdul1028/PixelKey
Author: Abdul Shaikh
Author-email: rasoolas2003@gmail.com
Classifier: Programming Language :: Python :: 3
Classifier: License :: OSI Approved :: MIT License
Classifier: Operating System :: OS Independent
Classifier: Development Status :: 3 - Alpha
Classifier: Intended Audience :: Developers
Classifier: Topic :: Security :: Cryptography
Classifier: Topic :: Multimedia :: Graphics
Requires-Python: >=3.8
License-File: LICENSE
Requires-Dist: Pillow>=10.3.0
Requires-Dist: cryptography>=3.4
